damm32/__init__.py
damm32/checksum.py
damm32/py.typed
damm32-1.2.1.dist-info/LICENSE
damm32-1.2.1.dist-info/WHEEL
damm32-1.2.1.dist-info/METADATA
damm32-1.2.1.dist-info/RECORD
