Metadata-Version: 2.1
Name: damm32
Version: 1.2.1
Summary: A pure-python implementation of the Damm Algorithm in Base 32.
Home-page: https://github.com/pyinv/damm32
License: MIT
Author: Dan Trickey
Author-email: dan@trickey.io
Requires-Python: >=3.6,<4.0
Classifier: License :: OSI Approved :: MIT License
Classifier: Operating System :: OS Independent
Classifier: Programming Language :: Python :: 3
Classifier: Programming Language :: Python :: 3.6
Classifier: Programming Language :: Python :: 3.7
Classifier: Programming Language :: Python :: 3.8
Classifier: Programming Language :: Python :: 3.9
Project-URL: Repository, https://github.com/pyinv/damm32
